get_vf/__init__.py
get_vf/__main__.py
get_vf/_version.py
get_vf/createdb.py
get_vf/defaults.py
get_vf/search.py
get_vf/utils.py
get_ancient_vf-0.0.2.dist-info/LICENSE
get_ancient_vf-0.0.2.dist-info/METADATA
get_ancient_vf-0.0.2.dist-info/WHEEL
get_ancient_vf-0.0.2.dist-info/entry_points.txt
get_ancient_vf-0.0.2.dist-info/top_level.txt
get_ancient_vf-0.0.2.dist-info/RECORD
