Metadata-Version: 2.1
Name: get-ancient-vf
Version: 0.0.2
Summary: A simple tool to map ancient reads against VFDB.
Home-page: https://github.com/genomewalker/get-ancient-vf
Author: Antonio Fernandez-Guerra
Author-email: antonio@metagenomics.eu
License: GNUv3
Keywords: get-ancient-vf
Platform: UNKNOWN
Classifier: Programming Language :: Python :: 3.7
Classifier: Programming Language :: Python :: 3.8
Classifier: Programming Language :: Python :: 3.9
Requires-Dist: pandas (>=1.3.4)
Requires-Dist: scipy (>=1.7.3)
Requires-Dist: tqdm (>=4.62.3)
Requires-Dist: numpy (>=1.21.4)
Requires-Dist: biopython (>=1.79)
Requires-Dist: requests (>=2.26.0)
